{"name":"Wheeler - Arm","description":"An arm equipped with deadly razor sharp blades.\n\nFinding the underground racing scene, Wheeler was in love from the moment he witnessed his first race. Now, as the wars ruined his life, Wheeler fights for whatever purpose he sees fit.\n\nThis NFT is part of the Contaverse gaming universe, learn more here: https://contaquest.com","image":"https://www.contaverse.com/Contaverse-NFT/Images/Robot-Parts/Wheeler/Arm00.png","properties":{"Item Type":"Robot Part","Equip Slot":"Arm","Rarity":"Common","Health":1.82,"Speed":0.54,"Damage":0.81,"Defense":0.81,"Weight":1.08,"Agility":0.54,"Primary Color":"37363D","Secondary Color":"EE5600","Behaviours":[],"Upgrades":[]}}